ourmind_audio/__init__.py
ourmind_audio/_core.py
ourmind_audio/py.typed
ourmind_audio/test_webm_repair.py
ourmind_audio-0.1.1.dist-info/LICENSE
ourmind_audio-0.1.1.dist-info/WHEEL
ourmind_audio-0.1.1.dist-info/METADATA
ourmind_audio-0.1.1.dist-info/RECORD
